mkjsfiddle/__init__.py
mkjsfiddle/parser.py
mkjsfiddle/plugin.py
mkjsfiddle-1.0.1.dist-info/LICENSE.txt
mkjsfiddle-1.0.1.dist-info/METADATA
mkjsfiddle-1.0.1.dist-info/WHEEL
mkjsfiddle-1.0.1.dist-info/entry_points.txt
mkjsfiddle-1.0.1.dist-info/top_level.txt
mkjsfiddle-1.0.1.dist-info/RECORD
