Metadata-Version: 2.1
Name: mkjsfiddle
Version: 1.0.1
Summary: An MkDocs plugin that lets you edit code fences in JSFiddle.
Home-page: https://github.com/stadiamaps/mkjsfiddle
Author: Stadia Maps
Author-email: info@stadiamaps.com
License: MIT
Keywords: mkdocs jsfiddle plugin
Classifier: Development Status :: 5 - Production/Stable
Classifier: Intended Audience :: Developers
Classifier: Topic :: Documentation
Classifier: Topic :: Software Development :: Documentation
Classifier: License :: OSI Approved :: MIT License
Classifier: Programming Language :: Python :: 3.8
Classifier: Programming Language :: Python :: 3.9
Classifier: Programming Language :: Python :: 3.10
Requires-Python: >=3.8, <4
License-File: LICENSE.txt
Requires-Dist: mkdocs
Provides-Extra: test
Requires-Dist: pytest ; extra == 'test'
